tensorfaux/__init__.py
tensorfaux/layers.py
tensorfaux/models.py
tensorfaux/optimizers.py
tensorfaux/util.py
tensorfaux-0.0.1.dist-info/METADATA
tensorfaux-0.0.1.dist-info/WHEEL
tensorfaux-0.0.1.dist-info/licenses/LICENSE
tensorfaux-0.0.1.dist-info/RECORD
