Metadata-Version: 2.1
Name: tensorfaux
Version: 0.0.1
Summary: A basic deep learning package
Project-URL: Homepage, https://rudyorre.github.io/TensorFaux:
Project-URL: Bug Tracker, https://github.com/rudyorre/TensorFaux/issues
Author-email: Rudy Orre <rudyorre@gmail.com>
License: Copyright (c) 2018 The Python Packaging Authority
Classifier: License :: OSI Approved :: MIT License
Classifier: Operating System :: OS Independent
Classifier: Programming Language :: Python :: 3
Requires-Python: >=3.7
